pytoolsz/__init__.py
pytoolsz/compress.py
pytoolsz/forecast.py
pytoolsz/frame.py
pytoolsz/graph.py
pytoolsz/handlepath.py
pytoolsz/ppTrans.py
pytoolsz/pretools.py
pytoolsz/saveExcel.py
pytoolsz/tsTools.py
pytoolsz/utils.py
pytoolsz/utob.py
szdatasets/__init__.py
szdatasets/utils.py
szdatasets/covid/__init__.py
szdatasets/covid/covid.csv
szdatasets/iris/__init__.py
szdatasets/iris/iris.zip
szdatasets/tstest/__init__.py
szdatasets/tstest/testtrain.csv
pytoolsz-0.3.14.dist-info/METADATA
pytoolsz-0.3.14.dist-info/WHEEL
pytoolsz-0.3.14.dist-info/licenses/LICENSE
pytoolsz-0.3.14.dist-info/RECORD
