Metadata-Version: 2.3
Name: pytoolsz
Version: 0.3.14
Summary: A set of Python Tools, mainly used to deal with work problems.
Author-email: Sidney Zhang <zly@lyzhang.me>
License: MulanPSL-2.0
Requires-Python: >=3.8
Requires-Dist: cartopy>=0.23.0
Requires-Dist: cmaps>=2.0.1
Requires-Dist: country-converter>=1.2
Requires-Dist: frykit>=0.6.7
Requires-Dist: imapclient>=3.0.1
Requires-Dist: matplotlib>=3.9.2
Requires-Dist: opencv-python>=4.11.0.86
Requires-Dist: openpyxl>=3.1.5
Requires-Dist: pdfplumber>=0.11.4
Requires-Dist: pendulum>=3.0.0
Requires-Dist: pillow>=10.4.0
Requires-Dist: pmdarima>=2.0.4
Requires-Dist: polars>=1.5.0
Requires-Dist: prophet>=1.1.5
Requires-Dist: py7zr>=0.22.0
Requires-Dist: pyarrow>=17.0.0
Requires-Dist: pycountry>=24.6.1
Requires-Dist: pywin32>=306
Requires-Dist: rich>=13.7.1
Requires-Dist: seaborn>=0.13.2
Requires-Dist: statsmodels>=0.14.2
Requires-Dist: thefuzz>=0.22.1
Requires-Dist: torch==2.3.1
Requires-Dist: torchvision==0.18.1
